wbDefcon/__init__.py
wbDefcon/undomanager.py
wbDefcon/misc/__init__.py
wbDefcon/misc/glyphnamelist.py
wbDefcon/objects/__init__.py
wbDefcon/objects/anchor.py
wbDefcon/objects/base.py
wbDefcon/objects/color.py
wbDefcon/objects/component.py
wbDefcon/objects/contour.py
wbDefcon/objects/dataSet.py
wbDefcon/objects/features.py
wbDefcon/objects/font.py
wbDefcon/objects/glyph.py
wbDefcon/objects/groups.py
wbDefcon/objects/guideline.py
wbDefcon/objects/image.py
wbDefcon/objects/imageSet.py
wbDefcon/objects/info.py
wbDefcon/objects/kerning.py
wbDefcon/objects/layer.py
wbDefcon/objects/layerSet.py
wbDefcon/objects/lib.py
wbDefcon/objects/point.py
wbDefcon/objects/uniData.py
wbDefcon/pens/__init__.py
wbDefcon/pens/lineIntersectionPen.py
wbDefcon/pens/marginPen.py
wbDefcon/pens/outlineTestPen.py
wbDefcon/pens/pointPen.py
wbDefcon/tools/__init__.py
wbDefcon/tools/conversion.py
wbDefcon/tools/glyph.py
wbDefcon/tools/representations.py
wbDefcon-0.2.6.dist-info/LICENSE
wbDefcon-0.2.6.dist-info/METADATA
wbDefcon-0.2.6.dist-info/WHEEL
wbDefcon-0.2.6.dist-info/top_level.txt
wbDefcon-0.2.6.dist-info/RECORD
