Metadata-Version: 2.1
Name: wbDefcon
Version: 0.2.6
Summary: Defcon for Workbench applications.
Home-page: https://gitlab.com/workbench2/WorkBenchExtensions/wbDefcon
Author: Andreas Eigendorf
License: MIT
Project-URL: Source, https://gitlab.com/workbench2/WorkBenchExtensions/wbDefcon
Project-URL: Documentation, https://workbench2.gitlab.io/WorkBenchExtensions/wbDefcon/
Project-URL: Tracker, https://gitlab.com/workbench2/WorkBenchExtensions/wbDefcon/-/issues
Keywords: workbench,wxPython,GUI
Platform: WIN32
Platform: WIN64
Platform: OSX
Platform: POSIX
Classifier: Development Status :: 4 - Beta
Classifier: License :: OSI Approved :: MIT License
Classifier: Operating System :: MacOS
Classifier: Operating System :: Microsoft :: Windows
Classifier: Operating System :: POSIX
Classifier: Environment :: MacOS X :: Cocoa
Classifier: Environment :: Win32 (MS Windows)
Classifier: Environment :: X11 Applications :: GTK
Classifier: Programming Language :: Python :: 3
Classifier: Programming Language :: Python :: 3.8
Classifier: Programming Language :: Python :: 3.9
Classifier: Programming Language :: Python :: 3.10
Classifier: Programming Language :: Python :: 3.11
Classifier: Programming Language :: Python :: 3.12
Classifier: Programming Language :: Python :: Implementation :: CPython
Classifier: Intended Audience :: Developers
Classifier: Topic :: Software Development :: Libraries
Classifier: Topic :: Software Development :: User Interfaces
Classifier: Topic :: Text Processing :: Fonts
Classifier: Topic :: Multimedia :: Graphics
Requires-Python: >=3.8
License-File: LICENSE
Requires-Dist: defcon>=0.10.3
Requires-Dist: fontParts>=0.12.1
Requires-Dist: feaASTools>=0.2.5
Requires-Dist: wbBase>=0.2.8
